configurationlib/__init__.py
configurationlib/configurationlib.py
configurationlib-1.2.1.dist-info/LICENSE
configurationlib-1.2.1.dist-info/METADATA
configurationlib-1.2.1.dist-info/WHEEL
configurationlib-1.2.1.dist-info/top_level.txt
configurationlib-1.2.1.dist-info/RECORD
