Metadata-Version: 2.1
Name: configurationlib
Version: 1.2.1
Summary: A simple configuration manager
Author: kokodev
Author-email: koko@kokodev.cc
Classifier: Programming Language :: Python :: 3
Classifier: License :: OSI Approved :: MIT License
Classifier: Operating System :: OS Independent
License-File: LICENSE
Requires-Dist: pyyaml
Requires-Dist: toml
Requires-Dist: configparser
